Metadata-Version: 2.1
Name: odoo14-addon-test-base-import-async
Version: 14.0.1.0.1
Summary: Test suite for base_import_async. Normally you don't need to install this.
Home-page: https://github.com/OCA/queue
Author: ACSONE SA/NV, Odoo Community Association (OCA)
Author-email: support@odoo-community.org
License: AGPL-3
Platform: UNKNOWN
Classifier: Programming Language :: Python
Classifier: Framework :: Odoo
Classifier: License :: OSI Approved :: GNU Affero General Public License v3
Classifier: Development Status :: 5 - Production/Stable
Requires-Python: >=3.6
Requires-Dist: odoo14-addon-base-import-async
Requires-Dist: odoo (<14.1dev,>=14.0a)
